spwc/__init__.py
spwc-0.9.0.dist-info/AUTHORS.rst
spwc-0.9.0.dist-info/LICENSE
spwc-0.9.0.dist-info/METADATA
spwc-0.9.0.dist-info/WHEEL
spwc-0.9.0.dist-info/entry_points.txt
spwc-0.9.0.dist-info/top_level.txt
spwc-0.9.0.dist-info/RECORD
